{"data":"{\"FennecAndroid\": {\"adi\": [1140, 1120, 74971, 4236017], \"channel\": [\"nightly\", \"aurora\", \"beta\", \"release\"], \"rateBrCo\": [110, 61, 1925, 66207], \"startup\": [36, 16, 600, 20782], \"versions\": [[\"41.0a1\"], [\"40.0a2\"], [\"38.0.5b4\", \"39.0b1\", \"39.0b2\"], [\"36.0.2\", \"36.0.3\", \"36.0.4\", \"37.0\", \"37.0.1\", \"37.0.2\", \"38.0\", \"38.0.1\", \"38.0.5\"]]}, \"Firefox\": {\"adi\": [49746, 112877, 2198496, 101780713], \"browser\": [1359, 1746, 44966, 1314030], \"channel\": [\"nightly\", \"aurora\", \"beta\", \"release\"], \"content\": [1619, 1455, 0, 180], \"plugincrash\": [20, 65, 2646, 76640], \"pluginhang\": [11, 45, 9043, 125830], \"rateBrCo\": [2978, 3201, 44966, 1314210], \"startup\": [338, 375, 8417, 217420], \"versions\": [[\"41.0a1\"], [\"40.0a2\"], [\"38.0.5b1\", \"38.0.5b2\", \"38.0.5b3\", \"38.0.5b99\", \"39.0b1\", \"39.0b2\"], [\"36.0.3\", \"36.0.4\", \"37.0\", \"37.0.1\", \"37.0.2\", \"38.0\", \"38.0.1\", \"38.0.5\"]]}}"}