{"data":"{\"FennecAndroid\": {\"adi\": [1201, 1274, 91633, 4496745], \"channel\": [\"nightly\", \"aurora\", \"beta\", \"release\"], \"rateBrCo\": [215, 217, 2809, 79818], \"startup\": [148, 107, 1058, 22715], \"versions\": [[\"43.0a1\", \"44.0a1\"], [\"42.0a2\", \"43.0a2\"], [\"41.0b10\", \"41.0b8\", \"42.0b1\", \"42.0b2\"], [\"39.0.2\", \"40.0\", \"40.0.3\", \"41.0\"]]}, \"Firefox\": {\"adi\": [45259, 117487, 2285395, 101436287], \"browser\": [738, 1338, 25269, 886500], \"channel\": [\"nightly\", \"aurora\", \"beta\", \"release\"], \"content\": [6316, 3127, 0, 590], \"plugincrash\": [17, 45, 1539, 64000], \"pluginhang\": [1, 37, 1580, 53050], \"rateBrCo\": [7054, 4465, 25269, 887090], \"startup\": [187, 253, 4656, 146160], \"versions\": [[\"43.0a1\", \"44.0a1\"], [\"42.0a2\", \"43.0a2\"], [\"41.0b7\", \"41.0b8\", \"41.0b9\", \"41.0b99\", \"42.0b1\", \"42.0b2\"], [\"39.0.3\", \"40.0\", \"40.0.1\", \"40.0.2\", \"40.0.3\", \"41.0\", \"41.0.1\"]]}}"}