{"data":"{\"FennecAndroid\": {\"adi\": [1608, 1407, 86529, 4125771], \"channel\": [\"nightly\", \"aurora\", \"beta\", \"release\"], \"rateBrCo\": [87, 92, 2237, 71332], \"startup\": [31, 28, 656, 21743], \"versions\": [[\"40.0a1\", \"41.0a1\"], [\"39.0a2\", \"40.0a2\"], [\"38.0.5b4\", \"38.0b10\", \"39.0b1\"], [\"36.0.2\", \"36.0.3\", \"36.0.4\", \"37.0\", \"37.0.1\", \"37.0.2\", \"38.0\", \"38.0.1\", \"38.0.5\"]]}, \"Firefox\": {\"adi\": [44216, 84281, 1915725, 73142910], \"browser\": [1620, 1599, 40107, 1051430], \"channel\": [\"nightly\", \"aurora\", \"beta\", \"release\"], \"content\": [1177, 1145, 0, 240], \"plugincrash\": [17, 70, 2462, 68130], \"pluginhang\": [12, 75, 7568, 123440], \"rateBrCo\": [2797, 2744, 40107, 1051670], \"startup\": [411, 332, 8419, 172740], \"versions\": [[\"40.0a1\", \"41.0a1\"], [\"39.0a2\", \"40.0a2\"], [\"38.0.5b1\", \"38.0.5b2\", \"38.0.5b3\", \"38.0.5b99\", \"38.0b99\", \"39.0b1\"], [\"36.0.3\", \"36.0.4\", \"37.0\", \"37.0.1\", \"37.0.2\", \"38.0\", \"38.0.1\", \"38.0.5\"]]}}"}