{"data":"{\"FennecAndroid\": {\"adi\": [1035, 1034, 84923, 4405294], \"channel\": [\"nightly\", \"aurora\", \"beta\", \"release\"], \"rateBrCo\": [156, 44, 1897, 65883], \"startup\": [131, 21, 491, 19222], \"versions\": [[\"42.0a1\"], [\"41.0a2\"], [\"40.0b1\", \"40.0b2\", \"40.0b4\", \"40.0b6\"], [\"38.0\", \"38.0.1\", \"38.0.5\", \"39.0\", \"39.0.1\", \"39.0.2\"]]}, \"Firefox\": {\"adi\": [43313, 104588, 1793624, 93521957], \"browser\": [1305, 1488, 23364, 923150], \"channel\": [\"nightly\", \"aurora\", \"beta\", \"release\"], \"content\": [11155, 1951, 69, 210], \"plugincrash\": [16, 37, 1226, 70850], \"pluginhang\": [9, 30, 5652, 81050], \"rateBrCo\": [12460, 3439, 23433, 923360], \"startup\": [357, 382, 3845, 142730], \"versions\": [[\"42.0a1\"], [\"41.0a2\"], [\"40.0b1\", \"40.0b2\", \"40.0b3\", \"40.0b4\", \"40.0b6\"], [\"38.0\", \"38.0.1\", \"38.0.5\", \"38.0.6\", \"39.0\"]]}}"}