{"data":"{\"FennecAndroid\": {\"adi\": [1152, 8831, 181161, 6853351], \"channel\": [\"nightly\", \"aurora\", \"beta\", \"release\"], \"rateBrCo\": [58, 184, 2505, 80646], \"startup\": [16, 60, 773, 20943], \"versions\": [[\"53.0a1\"], [\"52.0a2\"], [\"51.0b2\", \"51.0b4\", \"51.0b5\", \"51.0b7\"], [\"49.0.2\", \"50.0\", \"50.0.1\", \"50.0.2\", \"50.1.0\"]]}, \"Firefox\": {\"adi\": [23844, 61451, 1224380, 64531686], \"browser\": [543, 878, 9716, 552680], \"channel\": [\"nightly\", \"aurora\", \"beta\", \"release\"], \"content\": [2344, 3734, 3381, 251420], \"plugincrash\": [238, 612, 632, 52830], \"pluginhang\": [30, 91, 434, 35820], \"rateBrCo\": [2887, 4612, 13097, 804100], \"startup\": [244, 296, 6802, 116470], \"versions\": [[\"53.0a1\"], [\"52.0a2\"], [\"50.1.0b99\", \"51.0b2\", \"51.0b3\", \"51.0b4\", \"51.0b5\", \"51.0b6\", \"51.0b7\", \"51.0b8\"], [\"47.0.2\", \"49.0.2\", \"50.0\", \"50.0.1\", \"50.0.2\", \"50.1.0\"]]}}"}