{"data":"{\"FennecAndroid\": {\"adi\": [1346, 10388, 174336, 7543036], \"channel\": [\"nightly\", \"aurora\", \"beta\", \"release\"], \"rateBrCo\": [47, 194, 3458, 89276], \"startup\": [7, 67, 772, 18977], \"versions\": [[\"54.0a1\"], [\"53.0a2\"], [\"52.0b99\", \"52.0b11\", \"52.0b10\", \"52.0b8\", \"52.0b6\", \"52.0b5\", \"52.0b4\"], [\"52.0\", \"51.0.4\", \"51.0.3\", \"51.0.2\", \"51.0\", \"50.1.0\"]]}, \"Firefox\": {\"adi\": [30144, 88518, 1893313, 89470056], \"browser\": [470, 538, 12865, 479900], \"channel\": [\"nightly\", \"aurora\", \"beta\", \"release\"], \"content\": [380, 335, 3793, 256180], \"plugincrash\": [12, 13, 553, 41440], \"pluginhang\": [2, 12, 537, 22940], \"rateBrCo\": [850, 873, 16658, 736080], \"startup\": [187, 222, 3648, 94250], \"versions\": [[\"54.0a1\"], [\"53.0a2\"], [\"52.0b99\", \"52.0b9\", \"52.0b8\", \"52.0b7\", \"52.0b6\", \"52.0b5\", \"52.0b4\", \"52.0b3\"], [\"52.0\", \"51.0.1\", \"51.0\"]]}}"}